{"ID":320942,"Name":"Sofia Kenin","Country":"USA","DateOfBirth":"1998-11-14T00:00:00","Plays":"Right-Handed","CurrentRanking":48,"CareerHighRanking":48,"CareerHighRankingDate":"2018-10-29T00:00:00","SingleTitles":0,"PrizeMoney":881475.0,"CareerSinglesWon":141,"CareerSinglesLost":86,"RankingsHistory":[{"Year":2017,"Ranking":113},{"Year":2016,"Ranking":212},{"Year":2015,"Ranking":620}],"CurrentStats":{"Aces":51,"Double Faults":116,"1st Serve %":65.6,"1st Serve Points Won %":63.5,"2nd Serve Points Won %":46.7,"Break Points Saved %":52.6,"Service Game Won %":67.5,"Service Points Won %":57.8,"1st Return Points Won %":33.7,"2nd Return Points Won %":55.1,"Break Points Converted %":48.7,"Return Games Won %":33.9,"Return Points Won %":42.3}}