{"AsOf":"2018-11-05T00:00:00","ID":313796,"Name":"Anastasia Pavlyuchenkova","Country":"RUS","DateOfBirth":"1991-07-03T00:00:00","Plays":"Right-Handed","CurrentRanking":42,"CareerHighRanking":13,"CareerHighRankingDate":"2011-07-04T00:00:00","SingleTitles":12,"PrizeMoney":8769080.0,"CareerSinglesWon":396,"CareerSinglesLost":263,"RankingsHistory":[{"Year":2017,"Ranking":15},{"Year":2016,"Ranking":28},{"Year":2015,"Ranking":28},{"Year":2014,"Ranking":25},{"Year":2013,"Ranking":26},{"Year":2012,"Ranking":36},{"Year":2011,"Ranking":16},{"Year":2010,"Ranking":21},{"Year":2009,"Ranking":41},{"Year":2008,"Ranking":45},{"Year":2007,"Ranking":281},{"Year":2006,"Ranking":402}],"CurrentStats":{"Aces":109,"Double Faults":178,"1st Serve %":64.8,"1st Serve Points Won %":65.2,"2nd Serve Points Won %":44.5,"Break Points Saved %":57.4,"Service Game Won %":68.7,"Service Points Won %":57.9,"1st Return Points Won %":34.9,"2nd Return Points Won %":55.2,"Break Points Converted %":39.9,"Return Games Won %":32.4,"Return Points Won %":42.2},"GrandSlamHistory":null}