{"AsOf":"2019-01-14T00:00:00","ID":313402,"Name":"Caroline Wozniacki","Country":"DEN","DateOfBirth":"1990-07-11T00:00:00","Plays":"Right-Handed","CurrentRanking":3,"CareerHighRanking":1,"CareerHighRankingDate":"2010-10-11T00:00:00","SingleTitles":30,"PrizeMoney":33495723.0,"CareerSinglesWon":611,"CareerSinglesLost":248,"RankingsHistory":[{"Year":2018,"Ranking":3},{"Year":2017,"Ranking":3},{"Year":2016,"Ranking":19},{"Year":2015,"Ranking":17},{"Year":2014,"Ranking":8},{"Year":2013,"Ranking":10},{"Year":2012,"Ranking":10},{"Year":2011,"Ranking":1},{"Year":2010,"Ranking":1},{"Year":2009,"Ranking":4},{"Year":2008,"Ranking":12},{"Year":2007,"Ranking":64},{"Year":2006,"Ranking":237}],"CurrentStats":{"Aces":1,"Double_Faults":3,"1st_Serve_%":60.3,"1st_Serve_Points_Won_%":65.8,"2nd_Serve_Points_Won_%":52.1,"Break_Points_Saved_%":58.3,"Service_Game_Won_%":73.7,"Service_Points_Won_%":60.3,"1st_Return_Points_Won_%":39.1,"2nd_Return_Points_Won_%":53.7,"Break_Points_Converted %":28.6,"Return_Games_Won_%":33.3,"Return_Points_Won_%":44.7},"GrandSlamHistory":[{"GrandSlam":"Australian Open","GrandSlamSinglesWon":32,"GrandSlamSinglesLost":10,"GrandSlamResults":[{"Year":2018,"Result":"W"},{"Year":2017,"Result":"R32"},{"Year":2016,"Result":"R128"},{"Year":2015,"Result":"R64"},{"Year":2014,"Result":"R32"},{"Year":2013,"Result":"R16"},{"Year":2012,"Result":"QF"},{"Year":2011,"Result":"SF"},{"Year":2010,"Result":"R16"},{"Year":2009,"Result":"R32"},{"Year":2008,"Result":"R16"},{"Year":2007,"Result":"-"}]},{"GrandSlam":"French Open","GrandSlamSinglesWon":21,"GrandSlamSinglesLost":11,"GrandSlamResults":[{"Year":2018,"Result":"R16"},{"Year":2017,"Result":"QF"},{"Year":2016,"Result":"-"},{"Year":2015,"Result":"R64"},{"Year":2014,"Result":"R128"},{"Year":2013,"Result":"R64"},{"Year":2012,"Result":"R32"},{"Year":2011,"Result":"R32"},{"Year":2010,"Result":"QF"},{"Year":2009,"Result":"R32"},{"Year":2008,"Result":"R32"},{"Year":2007,"Result":"R128"}]},{"GrandSlam":"Wimbledon","GrandSlamSinglesWon":23,"GrandSlamSinglesLost":12,"GrandSlamResults":[{"Year":2018,"Result":"R64"},{"Year":2017,"Result":"R16"},{"Year":2016,"Result":"R128"},{"Year":2015,"Result":"R16"},{"Year":2014,"Result":"R16"},{"Year":2013,"Result":"R64"},{"Year":2012,"Result":"R128"},{"Year":2011,"Result":"R16"},{"Year":2010,"Result":"R16"},{"Year":2009,"Result":"R16"},{"Year":2008,"Result":"R32"},{"Year":2007,"Result":"R64"}]},{"GrandSlam":"US Open","GrandSlamSinglesWon":36,"GrandSlamSinglesLost":12,"GrandSlamResults":[{"Year":2018,"Result":"R64"},{"Year":2017,"Result":"R64"},{"Year":2016,"Result":"SF"},{"Year":2015,"Result":"R64"},{"Year":2014,"Result":"F"},{"Year":2013,"Result":"R32"},{"Year":2012,"Result":"R128"},{"Year":2011,"Result":"SF"},{"Year":2010,"Result":"SF"},{"Year":2009,"Result":"F"},{"Year":2008,"Result":"R16"},{"Year":2007,"Result":"R64"}]}]}