{"AsOf":"2019-11-04T00:00:00","ID":321454,"Name":"Greet Minnen","Country":"BEL","DateOfBirth":"1997-08-14T00:00:00","Plays":"N/A","CurrentRanking":123,"CareerHighRanking":120,"CareerHighRankingDate":"2019-08-12T00:00:00","SingleTitles":0,"PrizeMoney":191305.0,"CareerSinglesWon":194,"CareerSinglesLost":90,"RankingsHistory":[{"Year":2018,"Ranking":316},{"Year":2017,"Ranking":828},{"Year":2016,"Ranking":323},{"Year":2015,"Ranking":457},{"Year":2013,"Ranking":932}],"CurrentStats":{"Aces":42,"Double_Faults":36,"1st_Serve_%":58.8,"1st_Serve_Points_Won_%":67.8,"2nd_Serve_Points_Won_%":42.7,"Break_Points_Saved_%":60.0,"Service_Game_Won_%":68.5,"Service_Points_Won_%":57.4,"1st_Return_Points_Won_%":34.7,"2nd_Return_Points_Won_%":55.6,"Break_Points_Converted %":48.9,"Return_Games_Won_%":33.3,"Return_Points_Won_%":42.5},"GrandSlamHistory":[{"GrandSlam":"Australian Open","GrandSlamSinglesWon":0,"GrandSlamSinglesLost":0,"GrandSlamResults":[]},{"GrandSlam":"French Open","GrandSlamSinglesWon":0,"GrandSlamSinglesLost":0,"GrandSlamResults":[]},{"GrandSlam":"Wimbledon","GrandSlamSinglesWon":0,"GrandSlamSinglesLost":0,"GrandSlamResults":[]},{"GrandSlam":"US Open","GrandSlamSinglesWon":0,"GrandSlamSinglesLost":0,"GrandSlamResults":[]}]}