{"AsOf":"2019-06-17T00:00:00","ID":322222,"Name":"Liudmila Samsonova","Country":"RUS","DateOfBirth":"1998-11-11T00:00:00","Plays":"N/A","CurrentRanking":145,"CareerHighRanking":145,"CareerHighRankingDate":"2019-06-17T00:00:00","SingleTitles":0,"PrizeMoney":131484.0,"CareerSinglesWon":138,"CareerSinglesLost":82,"RankingsHistory":[{"Year":2018,"Ranking":180},{"Year":2017,"Ranking":552},{"Year":2016,"Ranking":1078},{"Year":2015,"Ranking":0},{"Year":2014,"Ranking":864}],"CurrentStats":{"Aces":8,"Double_Faults":3,"1st_Serve_%":59.3,"1st_Serve_Points_Won_%":59.4,"2nd_Serve_Points_Won_%":36.4,"Break_Points_Saved_%":46.2,"Service_Game_Won_%":53.3,"Service_Points_Won_%":50.0,"1st_Return_Points_Won_%":30.9,"2nd_Return_Points_Won_%":70.8,"Break_Points_Converted %":28.6,"Return_Games_Won_%":15.4,"Return_Points_Won_%":41.3},"GrandSlamHistory":[{"GrandSlam":"Australian Open","GrandSlamSinglesWon":0,"GrandSlamSinglesLost":0,"GrandSlamResults":[]},{"GrandSlam":"French Open","GrandSlamSinglesWon":0,"GrandSlamSinglesLost":1,"GrandSlamResults":[{"Year":2019,"Result":"R128"}]},{"GrandSlam":"Wimbledon","GrandSlamSinglesWon":0,"GrandSlamSinglesLost":0,"GrandSlamResults":[]},{"GrandSlam":"US Open","GrandSlamSinglesWon":0,"GrandSlamSinglesLost":0,"GrandSlamResults":[]}]}