{"AsOf":"2019-02-25T00:00:00","ID":314237,"Name":"Misaki Doi","Country":"JPN","DateOfBirth":"1991-04-29T00:00:00","Plays":"Left-Handed","CurrentRanking":120,"CareerHighRanking":30,"CareerHighRankingDate":"2016-10-10T00:00:00","SingleTitles":1,"PrizeMoney":2389223.0,"CareerSinglesWon":314,"CareerSinglesLost":276,"RankingsHistory":[{"Year":2018,"Ranking":139},{"Year":2017,"Ranking":119},{"Year":2016,"Ranking":38},{"Year":2015,"Ranking":60},{"Year":2014,"Ranking":122},{"Year":2013,"Ranking":89},{"Year":2012,"Ranking":97},{"Year":2011,"Ranking":106},{"Year":2010,"Ranking":158},{"Year":2009,"Ranking":200},{"Year":2008,"Ranking":613}],"CurrentStats":{"Aces":0,"Double_Faults":5,"1st_Serve_%":70.4,"1st_Serve_Points_Won_%":42.1,"2nd_Serve_Points_Won_%":43.8,"Break_Points_Saved_%":33.3,"Service_Game_Won_%":25.0,"Service_Points_Won_%":42.6,"1st_Return_Points_Won_%":29.2,"2nd_Return_Points_Won_%":43.8,"Break_Points_Converted %":66.7,"Return_Games_Won_%":25.0,"Return_Points_Won_%":35.0},"GrandSlamHistory":[{"GrandSlam":"Australian Open","GrandSlamSinglesWon":1,"GrandSlamSinglesLost":5,"GrandSlamResults":[{"Year":2019,"Result":"R128"},{"Year":2017,"Result":"R128"},{"Year":2016,"Result":"R128"},{"Year":2015,"Result":"-"},{"Year":2014,"Result":"R128"},{"Year":2013,"Result":"R64"},{"Year":2012,"Result":"-"},{"Year":2011,"Result":"-"},{"Year":2010,"Result":"-"}]},{"GrandSlam":"French Open","GrandSlamSinglesWon":1,"GrandSlamSinglesLost":6,"GrandSlamResults":[{"Year":2019,"Result":"-"},{"Year":2017,"Result":"R128"},{"Year":2016,"Result":"R128"},{"Year":2015,"Result":"R64"},{"Year":2014,"Result":"R128"},{"Year":2013,"Result":"R128"},{"Year":2012,"Result":"-"},{"Year":2011,"Result":"-"},{"Year":2010,"Result":"R128"}]},{"GrandSlam":"Wimbledon","GrandSlamSinglesWon":6,"GrandSlamSinglesLost":7,"GrandSlamResults":[{"Year":2019,"Result":"-"},{"Year":2017,"Result":"R128"},{"Year":2016,"Result":"R16"},{"Year":2015,"Result":"R128"},{"Year":2014,"Result":"R64"},{"Year":2013,"Result":"R128"},{"Year":2012,"Result":"R128"},{"Year":2011,"Result":"R32"},{"Year":2010,"Result":"-"}]},{"GrandSlam":"US Open","GrandSlamSinglesWon":1,"GrandSlamSinglesLost":6,"GrandSlamResults":[{"Year":2019,"Result":"-"},{"Year":2017,"Result":"R128"},{"Year":2016,"Result":"R128"},{"Year":2015,"Result":"R64"},{"Year":2014,"Result":"R128"},{"Year":2013,"Result":"R128"},{"Year":2012,"Result":"-"},{"Year":2011,"Result":"R128"},{"Year":2010,"Result":"-"}]}]}