{"AsOf":"2019-05-06T00:00:00","ID":322277,"Name":"Viktoria Kuzmova","Country":"SVK","DateOfBirth":"1998-05-11T00:00:00","Plays":"Right-Handed","CurrentRanking":46,"CareerHighRanking":43,"CareerHighRankingDate":"2019-03-04T00:00:00","SingleTitles":0,"PrizeMoney":822878.0,"CareerSinglesWon":232,"CareerSinglesLost":103,"RankingsHistory":[{"Year":2018,"Ranking":56},{"Year":2017,"Ranking":132},{"Year":2016,"Ranking":225},{"Year":2015,"Ranking":440},{"Year":2014,"Ranking":703}],"CurrentStats":{"Aces":123,"Double_Faults":93,"1st_Serve_%":55.8,"1st_Serve_Points_Won_%":67.8,"2nd_Serve_Points_Won_%":45.0,"Break_Points_Saved_%":53.2,"Service_Game_Won_%":66.1,"Service_Points_Won_%":57.7,"1st_Return_Points_Won_%":35.3,"2nd_Return_Points_Won_%":54.0,"Break_Points_Converted %":41.8,"Return_Games_Won_%":31.1,"Return_Points_Won_%":42.4},"GrandSlamHistory":[{"GrandSlam":"Australian Open","GrandSlamSinglesWon":1,"GrandSlamSinglesLost":2,"GrandSlamResults":[{"Year":2019,"Result":"R64"},{"Year":2018,"Result":"R128"},{"Year":2017,"Result":"-"}]},{"GrandSlam":"French Open","GrandSlamSinglesWon":1,"GrandSlamSinglesLost":1,"GrandSlamResults":[{"Year":2019,"Result":"-"},{"Year":2018,"Result":"R64"},{"Year":2017,"Result":"-"}]},{"GrandSlam":"Wimbledon","GrandSlamSinglesWon":0,"GrandSlamSinglesLost":1,"GrandSlamResults":[{"Year":2019,"Result":"-"},{"Year":2018,"Result":"R128"},{"Year":2017,"Result":"-"}]},{"GrandSlam":"US Open","GrandSlamSinglesWon":0,"GrandSlamSinglesLost":2,"GrandSlamResults":[{"Year":2019,"Result":"-"},{"Year":2018,"Result":"R128"},{"Year":2017,"Result":"R128"}]}]}