{"AsOf":"2018-12-31T00:00:00","ID":324188,"Name":"Francesca Di Lorenzo","Country":"USA","DateOfBirth":"1997-07-22T00:00:00","Plays":"N/A","CurrentRanking":165,"CareerHighRanking":150,"CareerHighRankingDate":"2018-10-22T00:00:00","SingleTitles":0,"PrizeMoney":193269.0,"CareerSinglesWon":87,"CareerSinglesLost":51,"RankingsHistory":[{"Year":2018,"Ranking":166},{"Year":2017,"Ranking":302},{"Year":2016,"Ranking":346},{"Year":2015,"Ranking":863}],"CurrentStats":{"Aces":0,"Double_Faults":0,"1st_Serve_%":0.0,"1st_Serve_Points_Won_%":0.0,"2nd_Serve_Points_Won_%":0.0,"Break_Points_Saved_%":0.0,"Service_Game_Won_%":0.0,"Service_Points_Won_%":0.0,"1st_Return_Points_Won_%":0.0,"2nd_Return_Points_Won_%":0.0,"Break_Points_Converted %":0.0,"Return_Games_Won_%":0.0,"Return_Points_Won_%":0.0},"GrandSlamHistory":null}