{"AsOf":"2018-12-31T00:00:00","ID":316296,"Name":"Viktorija Golubic","Country":"SUI","DateOfBirth":"1992-10-16T00:00:00","Plays":"Right-Handed","CurrentRanking":104,"CareerHighRanking":51,"CareerHighRankingDate":"2017-04-03T00:00:00","SingleTitles":1,"PrizeMoney":1093228.0,"CareerSinglesWon":284,"CareerSinglesLost":189,"RankingsHistory":[{"Year":2018,"Ranking":92},{"Year":2017,"Ranking":128},{"Year":2016,"Ranking":57},{"Year":2015,"Ranking":178},{"Year":2014,"Ranking":227},{"Year":2013,"Ranking":193},{"Year":2012,"Ranking":609},{"Year":2011,"Ranking":564},{"Year":2010,"Ranking":936}],"CurrentStats":{"Aces":0,"Double_Faults":0,"1st_Serve_%":0.0,"1st_Serve_Points_Won_%":0.0,"2nd_Serve_Points_Won_%":0.0,"Break_Points_Saved_%":0.0,"Service_Game_Won_%":0.0,"Service_Points_Won_%":0.0,"1st_Return_Points_Won_%":0.0,"2nd_Return_Points_Won_%":0.0,"Break_Points_Converted %":0.0,"Return_Games_Won_%":0.0,"Return_Points_Won_%":0.0},"GrandSlamHistory":null}